azureiai/__init__.py
azureiai/__main__.py
azureiai/ama_app.py
azureiai/azpc_app.py
azureiai/managed_apps/__init__.py
azureiai/managed_apps/counter.py
azureiai/managed_apps/managed_app.py
azureiai/managed_apps/offer.py
azureiai/managed_apps/swagger.py
azureiai/managed_apps/utils.py
azureiai/managed_apps/commands/__init__.py
azureiai/managed_apps/commands/common.py
azureiai/managed_apps/commands/create.py
azureiai/managed_apps/commands/delete.py
azureiai/managed_apps/commands/list.py
azureiai/managed_apps/commands/publish.py
azureiai/managed_apps/commands/status.py
azureiai/managed_apps/commands/update.py
azureiai/managed_apps/confs/__init__.py
azureiai/managed_apps/confs/listing.py
azureiai/managed_apps/confs/listing_image.py
azureiai/managed_apps/confs/offer_configurations.py
azureiai/managed_apps/confs/product_availability.py
azureiai/managed_apps/confs/properties.py
azureiai/managed_apps/confs/reseller_configuration.py
azureiai/managed_apps/confs/variant/__init__.py
azureiai/managed_apps/confs/variant/feature_availability.py
azureiai/managed_apps/confs/variant/markets.json
azureiai/managed_apps/confs/variant/offer_listing.py
azureiai/managed_apps/confs/variant/package.py
azureiai/managed_apps/confs/variant/variant_plan_configuration.py
azureiai/partner_center/__init__.py
azureiai/partner_center/abstract_offer.py
azureiai/partner_center/abstract_parser.py
azureiai/partner_center/cli_parser.py
azureiai/partner_center/offer.py
azureiai/partner_center/offers_api.py
azureiai/partner_center/plan.py
azureiai/partner_center/submission.py
azureiai/partner_center/offers/__init__.py
azureiai/partner_center/offers/application.py
azureiai/partner_center/offers/container.py
azureiai/partner_center/offers/managed_app.py
azureiai/partner_center/offers/solution_template.py
azureiai/partner_center/offers/virtual_machine.py
swagger_client/__init__.py
swagger_client/api_client.py
swagger_client/configuration.py
swagger_client/rest.py
swagger_client/api/__init__.py
az_partner_center_cli-0.2.5.dist-info/LICENSE
az_partner_center_cli-0.2.5.dist-info/METADATA
az_partner_center_cli-0.2.5.dist-info/WHEEL
az_partner_center_cli-0.2.5.dist-info/entry_points.txt
az_partner_center_cli-0.2.5.dist-info/top_level.txt
az_partner_center_cli-0.2.5.dist-info/RECORD
