Metadata-Version: 2.1
Name: az-partner-center-cli
Version: 0.2.5
Summary: https://api.partner.microsoft.com/v1.0/ingestion
Home-page: UNKNOWN
Author-email: 
License: UNKNOWN
Keywords: Swagger,https://api.partner.microsoft.com/v1.0/ingestion
Platform: UNKNOWN
Requires-Python: >=3.7,<4
Requires-Dist: azure-mgmt-deploymentmanager
Requires-Dist: azure-mgmt-resource
Requires-Dist: azure-storage-blob
Requires-Dist: azure-identity (>=1.2.0)
Requires-Dist: urllib3 (>=1.15)
Requires-Dist: six (>=1.10)
Requires-Dist: certifi
Requires-Dist: python-dateutil
Requires-Dist: requests
Requires-Dist: pyyaml
Requires-Dist: pygments
Requires-Dist: wget
Requires-Dist: adal
Requires-Dist: cryptography (>=3.3.1)
